README.rst
mylittlehelpers.py
setup.cfg
setup.py
mylittlehelpers.egg-info/PKG-INFO
mylittlehelpers.egg-info/SOURCES.txt
mylittlehelpers.egg-info/dependency_links.txt
mylittlehelpers.egg-info/requires.txt
mylittlehelpers.egg-info/top_level.txt