Metadata-Version: 1.2
Name: mylittlehelpers
Version: 1.0.17.dev0
Summary: Just some helper functions that I expect to use across projects
Home-page: https://github.com/jjorissen52/mylittlehelpers
Author: John-Paul Jorissen
Author-email: jjorissen52@gmail.com
License: Apache
Platform: UNKNOWN
Classifier: Development Status :: 3 - Alpha
Classifier: Intended Audience :: Developers
Classifier: Programming Language :: Python :: 3.6
Classifier: Operating System :: Microsoft :: Windows :: Windows 10
Classifier: Operating System :: POSIX :: Linux
Classifier: Topic :: Office/Business
Classifier: License :: OSI Approved :: Apache Software License
Classifier: Programming Language :: Python :: 3.6
Requires-Python: >=3.6
